muvfde/__init__.py
muvfde/_version.py
muvfde/muvfde_ext.abi3.so
muvfde/muvfde_ext.pyi
muvfde/py.typed
muvfde-0.0.9.dist-info/METADATA
muvfde-0.0.9.dist-info/WHEEL
muvfde-0.0.9.dist-info/RECORD
muvfde-0.0.9.dist-info/licenses/LICENSE
