Metadata-Version: 2.4
Name: muvfde
Version: 0.0.9
Summary: A Python library to generate Fixed Dimensional Embeddings for Multi-dimensional embedding vectors based on Google Muvera.
Author-Email: Arjun Variar <accio.arjun@gmail.com>
License-Expression: Apache-2.0
License-File: LICENSE
Classifier: Programming Language :: Python :: 3
Classifier: Programming Language :: Python :: 3.10
Classifier: Programming Language :: Python :: 3.11
Classifier: Programming Language :: Python :: 3.12
Classifier: Programming Language :: Python :: 3.13
Classifier: Programming Language :: Python :: Implementation :: CPython
Classifier: Programming Language :: C++
Classifier: Topic :: Software Development :: Libraries :: Python Modules
Classifier: Topic :: Scientific/Engineering :: Artificial Intelligence
Classifier: Topic :: Software Development :: Libraries
Classifier: Topic :: Utilities
Project-URL: Homepage, https://github.com/viig99/muvfde
Requires-Python: >=3.10
